{
  "schemaVersion": 1,
  "provenance": {
    "project": "ldtteam/minecolonies",
    "commit": "b2fa2b6232ca33944d1489827e95ea5b40328325",
    "minecraftVersion": "1.20.1",
    "license": "GPL-3.0",
    "structurize": {
      "version": "1.20.1-1.0.806-snapshot",
      "tag": "v1.20.1-1.0.806-snapshot",
      "commit": "8f6cad27f311eec2d8aee8b7c7bd58aa52edcd84",
      "categoryOrdering": "StructurePacks.getCategories sorts by Category.toString (subPath)",
      "blueprintOrdering": "StructurePacks.getBlueprints sorts by Blueprint.getFileName"
    },
    "sources": {
      "blueprints": "src/main/resources/blueprints/minecolonies",
      "serverConfiguration": "src/main/java/com/minecolonies/api/configuration/ServerConfiguration.java",
      "chunkClaims": "src/main/java/com/minecolonies/core/util/ChunkDataHelper.java",
      "buildingClaims": "src/main/java/com/minecolonies/core/colony/buildings/AbstractBuilding.java",
      "registeredBuildings": "src/main/java/com/minecolonies/apiimp/initializer/ModBuildingsInitializer.java",
      "blueprintPlacement": "src/main/java/com/minecolonies/core/placementhandlers/main/SurvivalHandler.java",
      "townHallClaims": "src/main/java/com/minecolonies/core/colony/buildings/workerbuildings/BuildingTownHall.java",
      "guardTowerClaims": "src/main/java/com/minecolonies/core/colony/buildings/workerbuildings/BuildingGuardTower.java",
      "guardPatrol": "src/main/java/com/minecolonies/core/colony/buildings/AbstractBuildingGuards.java",
      "guardProtection": "src/main/java/com/minecolonies/core/colony/managers/RegisteredStructureManager.java",
      "colonyMapRanges": "src/main/java/com/minecolonies/core/client/gui/map/WindowColonyMap.java"
    }
  },
  "rules": {
    "chunkSizeBlocks": 16,
    "defaults": {
      "initialColonyRadiusChunks": 4,
      "maximumColonyRadiusChunks": 20,
      "minimumColonyDistanceChunks": 8
    },
    "limits": {
      "initialColonyRadiusChunks": {
        "min": 1,
        "max": 15
      },
      "maximumColonyRadiusChunks": {
        "min": 1,
        "max": 250
      },
      "minimumColonyDistanceChunks": {
        "min": 1,
        "max": 200
      }
    },
    "buildingClaimRadiusByLevel": [
      1,
      1,
      1,
      2,
      2
    ],
    "townHallClaimRadiusByLevel": [
      1,
      1,
      2,
      3,
      5
    ],
    "guardTowerClaimRadiusByLevel": [
      2,
      3,
      3,
      4,
      5
    ],
    "gateHouseClaimRadiusByLevel": [
      1,
      1,
      2
    ],
    "barracksClaimRadiusByLevel": [
      2,
      2,
      2,
      2,
      2
    ],
    "barracksTowerClaimRadiusByLevel": [
      0,
      0,
      0,
      0,
      0
    ],
    "guardPatrolRadiusBlocksByLevel": [
      80,
      110,
      140,
      170,
      200
    ],
    "claimingBuildingTypes": [
      "alchemist",
      "archery",
      "baker",
      "barracks",
      "barrackstower",
      "beekeeper",
      "blacksmith",
      "builder",
      "chickenherder",
      "combatacademy",
      "composter",
      "concretemixer",
      "cook",
      "cowboy",
      "crusher",
      "deliveryman",
      "dyer",
      "enchanter",
      "farmer",
      "fisherman",
      "fletcher",
      "florist",
      "gatehouse",
      "glassblower",
      "graveyard",
      "guard_tower",
      "hospital",
      "kitchen",
      "library",
      "lumberjack",
      "mechanic",
      "mediumquarry",
      "miner",
      "mysticalsite",
      "netherworker",
      "plantation",
      "postbox",
      "rabbithutch",
      "residence",
      "sawmill",
      "school",
      "shepherd",
      "sifter",
      "simplequarry",
      "smeltery",
      "stable",
      "stash",
      "stonemason",
      "stonesmeltery",
      "swineherder",
      "tavern",
      "town_hall",
      "university",
      "warehouse"
    ]
  },
  "stylePacks": [
    {
      "id": "acacia",
      "name": "Urban Savanna",
      "description": "In the heat of the Savanna, you'll find the perfect spot for a place to live. Making use of the native acacia trees, this style is semi-modern, more of a ranch style than an urban one.",
      "authors": [
        "John Reiher"
      ],
      "version": "1",
      "categoryOrder": [
        "agriculture",
        "craftsmanship",
        "decorations",
        "education",
        "fundamentals",
        "infrastructure",
        "military",
        "mystic",
        "walls"
      ],
      "variantCount": 155,
      "levelCount": 401
    },
    {
      "id": "ancientathens",
      "name": "Ancient Athens",
      "description": "In the Age of Aristotle and Plato, a great Mediterranean power dominates the Aegean Sea. Start your own Hellenistic Empire and rival the great Greek capital.",
      "authors": [
        "John Reiher",
        "Pixblockus",
        "_Raycoms_",
        "Thodor12"
      ],
      "version": "4",
      "categoryOrder": [
        "agriculture",
        "craftsmanship",
        "decorations",
        "education",
        "fundamentals",
        "infrastructure",
        "military",
        "mystic",
        "walls"
      ],
      "variantCount": 238,
      "levelCount": 528
    },
    {
      "id": "birch",
      "name": "Urban Birch",
      "description": "[Beginner] This style is a perfect fit when you plan to settle closely to a birch forest and are looking for a modern look.",
      "authors": [
        "Raycoms",
        "Aravan",
        "Cugo"
      ],
      "version": "1",
      "categoryOrder": [
        "agriculture",
        "craftsmanship",
        "decorations",
        "education",
        "fundamentals",
        "infrastructure",
        "military",
        "mystic",
        "walls"
      ],
      "variantCount": 126,
      "levelCount": 326
    },
    {
      "id": "caledonia",
      "name": "Caledonia",
      "description": "Welcome to Caledonia! A beautiful mixture of Colonial British and French architecture, nestled in the South Pacific. An urban style, suited for dense housing and grand buildings of all types.",
      "authors": [
        "Thaylar"
      ],
      "version": "1",
      "categoryOrder": [
        "agriculture",
        "craftsmanship",
        "decorations",
        "education",
        "fundamentals",
        "infrastructure",
        "military",
        "mystic",
        "walls"
      ],
      "variantCount": 178,
      "levelCount": 432
    },
    {
      "id": "cavern",
      "name": "Cavern",
      "description": "[Advanced] Delve into the depths of the earth with this interconnecting style! If you like Lego, love Tetris and are obsessed with organization this is the style for you.",
      "authors": [
        "LadyShatana"
      ],
      "version": "1",
      "categoryOrder": [
        "agriculture",
        "craftsmanship",
        "decorations",
        "education",
        "fundamentals",
        "infrastructure",
        "military",
        "mystic",
        "walls"
      ],
      "variantCount": 279,
      "levelCount": 719
    },
    {
      "id": "colonial",
      "name": "Colonial",
      "description": "[Beginner] This is the default MineColonies Style. Set in the early colonial age it mixes elements of neo-classical architecture with an early industrial flavor",
      "authors": [
        "Raycoms",
        "John Reiher",
        "SomeAddons",
        "Thodor12"
      ],
      "version": "1",
      "categoryOrder": [
        "agriculture",
        "craftsmanship",
        "decorations",
        "education",
        "fundamentals",
        "infrastructure",
        "military",
        "mystic",
        "walls"
      ],
      "variantCount": 159,
      "levelCount": 510
    },
    {
      "id": "darkoak",
      "name": "Dark Oak Treehouse",
      "description": "If building in a spooky forest is an idea that makes you smile, this is the colony design for you! This interconnected treetop set blends in to the surrounding dark oak forest, yet keeps your citizens safe at the same time.",
      "authors": [
        "Annie",
        "Cugo"
      ],
      "version": "1",
      "categoryOrder": [
        "agriculture",
        "craftsmanship",
        "decorations",
        "education",
        "fundamentals",
        "infrastructure",
        "military",
        "mystic",
        "walls"
      ],
      "variantCount": 91,
      "levelCount": 291
    },
    {
      "id": "fortress",
      "name": "Fortress",
      "description": "[Advanced] Every Monarch dreams of having the perfect capital city, where everyone works hard and everything is clean and organized. No pesky holes to fall into, no random heaps of dirt to detour around.",
      "authors": [
        "Aravan"
      ],
      "version": "1",
      "categoryOrder": [
        "agriculture",
        "craftsmanship",
        "decorations",
        "education",
        "fundamentals",
        "infrastructure",
        "military",
        "mystic",
        "walls"
      ],
      "variantCount": 167,
      "levelCount": 461
    },
    {
      "id": "incan",
      "name": "Incan",
      "description": "Conquer the Andes and grow your own Incan empire! Buildings should be placed on or into the mountain ranges of your growing empire.",
      "authors": [
        "Raycoms",
        "John Reiher",
        "SomeAddons"
      ],
      "version": "1",
      "categoryOrder": [
        "agriculture",
        "craftsmanship",
        "decorations",
        "education",
        "fundamentals",
        "infrastructure",
        "military",
        "mystic",
        "walls"
      ],
      "variantCount": 131,
      "levelCount": 331
    },
    {
      "id": "jungle",
      "name": "Jungle Treehouse",
      "description": "Live like the Swiss Family Robinson, or your favorite SciFi movie franchise tree dwellers! This style builds around the native Jungle trees, though you will have to plant your own in many cases. Link the buildings with skyways over the undergrowth of the jungle canopy.",
      "authors": [
        "John Reiher",
        "assisted by Raycoms & Pixblockus"
      ],
      "version": "1",
      "categoryOrder": [
        "agriculture",
        "craftsmanship",
        "decorations",
        "education",
        "fundamentals",
        "infrastructure",
        "military",
        "mystic",
        "walls"
      ],
      "variantCount": 122,
      "levelCount": 410
    },
    {
      "id": "lostcity",
      "name": "Lost Mesa City",
      "description": "Resurrect the Ruins of the Lost City and restore the Empire to its lost Glory!",
      "authors": [
        "Raycoms",
        "John Reiher",
        "SomeAddons"
      ],
      "version": "1",
      "categoryOrder": [
        "agriculture",
        "craftsmanship",
        "decorations",
        "education",
        "fundamentals",
        "infrastructure",
        "military",
        "mystic",
        "walls"
      ],
      "variantCount": 209,
      "levelCount": 395
    },
    {
      "id": "medievalbirch",
      "name": "Medieval Birch",
      "description": "[Intermediate] Hear ye! A new castle emerges! Find a Good spot near a river and a forest and build your own medieval town! Alt townhall is a castle and regular one's a manor, some buildings are better placed near water and mind the size of the university and library! Those usually go well placed together.",
      "authors": [
        "Carlansor"
      ],
      "version": "1",
      "categoryOrder": [
        "agriculture",
        "craftsmanship",
        "decorations",
        "education",
        "fundamentals",
        "infrastructure",
        "military",
        "mystic",
        "walls"
      ],
      "variantCount": 95,
      "levelCount": 395
    },
    {
      "id": "medievaldarkoak",
      "name": "Medieval Dark Oak",
      "description": "[Intermediate] Hear ye! A new castle emerges! Find a Good spot near a river and a forest and build your own medieval town! Alt townhall is a castle and regular one's a manor, some buildings are better placed near water and mind the size of the university and library! Those usually go well placed together.",
      "authors": [
        "Carlansor"
      ],
      "version": "1",
      "categoryOrder": [
        "agriculture",
        "craftsmanship",
        "decorations",
        "education",
        "fundamentals",
        "infrastructure",
        "military",
        "mystic",
        "walls"
      ],
      "variantCount": 94,
      "levelCount": 394
    },
    {
      "id": "medievaloak",
      "name": "Medieval Oak",
      "description": "[Intermediate] Hear ye! A new castle emerges! Find a Good spot near a river and a forest and build your own medieval town! Alt townhall is a castle and regular one's a manor, some buildings are better placed near water and mind the size of the university and library! Those usually go well placed together.",
      "authors": [
        "Carlansor"
      ],
      "version": "1",
      "categoryOrder": [
        "agriculture",
        "craftsmanship",
        "decorations",
        "education",
        "fundamentals",
        "infrastructure",
        "military",
        "mystic",
        "walls"
      ],
      "variantCount": 116,
      "levelCount": 440
    },
    {
      "id": "medievalspruce",
      "name": "Medieval Spruce",
      "description": "[Intermediate] Hear ye! A new castle emerges! Find a Good spot near a river and a forest and build your own medieval town! Alt townhall is a castle and regular one's a manor, some buildings are better placed near water and mind the size of the university and library! Those usually go well placed together.",
      "authors": [
        "Carlansor"
      ],
      "version": "1",
      "categoryOrder": [
        "agriculture",
        "craftsmanship",
        "decorations",
        "education",
        "fundamentals",
        "infrastructure",
        "military",
        "mystic",
        "walls"
      ],
      "variantCount": 97,
      "levelCount": 405
    },
    {
      "id": "nordic",
      "name": "Nordic Spruce",
      "description": "The Norsemen are back and are looking for a new Leader. Create a flourishing Norsemen Empire and strike fear in the hearts of your Neighbors!",
      "authors": [
        "Luna",
        "John Reiher"
      ],
      "version": "1",
      "categoryOrder": [
        "agriculture",
        "craftsmanship",
        "decorations",
        "education",
        "fundamentals",
        "infrastructure",
        "military",
        "mystic",
        "walls"
      ],
      "variantCount": 136,
      "levelCount": 406
    },
    {
      "id": "original",
      "name": "Minecolonies Original",
      "description": "[Beginner] This is the Classic MineColonies Style. It is simplistic in nature and serves a lot of the essential blueprints to raiders, miners, etc.",
      "authors": [
        "many"
      ],
      "version": "1",
      "categoryOrder": [
        "agriculture",
        "craftsmanship",
        "decorations",
        "education",
        "fundamentals",
        "infrastructure",
        "military",
        "mystic",
        "walls"
      ],
      "variantCount": 260,
      "levelCount": 550
    },
    {
      "id": "pagoda",
      "name": "Pagoda",
      "description": "Construct your Pagoda Empire and take over all the Cherry Blossom Biomes you can find!",
      "authors": [
        "Thaylar"
      ],
      "version": "1",
      "categoryOrder": [
        "agriculture",
        "craftsmanship",
        "decorations",
        "education",
        "fundamentals",
        "infrastructure",
        "military",
        "mystic",
        "walls"
      ],
      "variantCount": 196,
      "levelCount": 455
    },
    {
      "id": "sandstone",
      "name": "Desert Oasis",
      "description": "It's 1001 Nights. Pack in your Magic Carpet and build up your own Desert Empire!",
      "authors": [
        "Raycoms",
        "John Reiher",
        "SomeAddons",
        "AravanFox",
        "Moobien"
      ],
      "version": "1",
      "categoryOrder": [
        "agriculture",
        "craftsmanship",
        "decorations",
        "education",
        "fundamentals",
        "infrastructure",
        "military",
        "mystic",
        "walls"
      ],
      "variantCount": 156,
      "levelCount": 384
    },
    {
      "id": "shire",
      "name": "Shire",
      "description": "Welcome to the Shire, where there's mutton to eat, beer to drink, and a nice shady tree to rest under. Pull up a chair and rest up, soon it will be time for Elevenses..",
      "authors": [
        "Daddy_P1G",
        "JohnReiher",
        "and others"
      ],
      "version": "1",
      "categoryOrder": [
        "agriculture",
        "craftsmanship",
        "decorations",
        "education",
        "fundamentals",
        "infrastructure",
        "military",
        "mystic",
        "walls"
      ],
      "variantCount": 157,
      "levelCount": 395
    },
    {
      "id": "spacewars",
      "name": "Space Wars",
      "description": "[Advanced] It's Space Wars baby! Settle down your favorite desert planet and follow the motto: \"Go Big or Go Home!\" This style is not for the weak of heart, as it uses a lot of resources to build everything. Make sure it's a desert that you build this in.",
      "authors": [
        "JohnReiher & Raycoms"
      ],
      "version": "1",
      "categoryOrder": [
        "agriculture",
        "craftsmanship",
        "decorations",
        "education",
        "fundamentals",
        "infrastructure",
        "military",
        "mystic",
        "walls"
      ],
      "variantCount": 126,
      "levelCount": 318
    },
    {
      "id": "truedwarven",
      "name": "Stalactite Caves",
      "description": "This is the perfect pack for all the cave dwellers. Build up your colony and let your builder take care of the Stalactites.",
      "authors": [
        "Luna"
      ],
      "version": "1",
      "categoryOrder": [
        "agriculture",
        "craftsmanship",
        "decorations",
        "education",
        "fundamentals",
        "infrastructure",
        "military",
        "mystic",
        "walls"
      ],
      "variantCount": 65,
      "levelCount": 235
    },
    {
      "id": "warped",
      "name": "Warped Netherlands",
      "description": "The perfect pack to build up a colony in the nether. Beware of Zombified Piglins!",
      "authors": [
        "Cugo"
      ],
      "version": "1",
      "categoryOrder": [
        "agriculture",
        "craftsmanship",
        "decorations",
        "education",
        "fundamentals",
        "infrastructure",
        "military",
        "mystic",
        "walls"
      ],
      "variantCount": 70,
      "levelCount": 264
    }
  ]
}
